{"rooms":{"BkCxel8Fb":{"remainingCards":[],"started":true,"roomName":"dupa chuj","mode":"std","cardTimeout":0,"hash":"BkCxel8Fb","crossed":[],"players":{"NfIYGMqZ6u2t4ymuYB6vADJDVMkIfOJm":{"name":"dupa","io":[]}},"scoreboard":{"NfIYGMqZ6u2t4ymuYB6vADJDVMkIfOJm":{"score":1,"name":"dupa"}},"onBoard":[]},"BJxs0eUKb":{"remainingCards":[[1,0,0,1],[2,0,0,0],[0,2,1,1],[1,0,1,2],[2,1,1,2],[0,0,1,0],[0,1,0,2],[2,1,2,2],[1,0,1,1],[0,1,0,1],[2,2,1,2],[1,1,0,0],[0,1,2,0],[2,1,1,1],[0,0,2,2],[1,1,0,2],[0,0,0,1],[1,2,1,1],[0,2,0,2],[2,0,1,0],[2,0,2,2],[2,2,2,0],[1,1,2,2],[1,0,2,2],[1,0,2,0],[2,2,0,2],[2,0,2,1],[0,1,1,0],[0,0,1,1],[2,2,1,1],[1,0,0,2],[1,1,0,1],[2,1,0,1],[1,2,2,1],[1,1,1,2],[1,2,2,0],[0,0,2,0],[0,2,1,0],[2,2,2,2],[1,1,2,0],[2,1,2,0],[2,2,2,1],[1,0,2,1],[0,1,2,1],[0,1,1,2],[0,1,2,2],[1,2,0,0],[2,1,2,1],[0,0,0,0],[0,1,0,0],[1,2,0,1],[0,0,1,2],[1,2,0,2],[1,2,1,0],[0,2,2,2],[0,2,0,1],[0,2,1,2],[2,0,0,2],[1,0,0,0],[2,1,0,2],[1,2,2,2],[0,0,0,2],[0,2,2,1]],"started":true,"roomName":"dupa chuj","mode":"std","cardTimeout":0,"hash":"BJxs0eUKb","crossed":[],"players":{"NfIYGMqZ6u2t4ymuYB6vADJDVMkIfOJm":{"name":"dupa","io":["eUQMESWr5qWwWDAfAAAd"]}},"scoreboard":{"NfIYGMqZ6u2t4ymuYB6vADJDVMkIfOJm":{"score":2,"name":"dupa"}},"onBoard":[[0,1,1,1],[1,1,1,0],[2,0,1,1],[2,0,0,1],[2,0,1,2],[1,0,1,0],[1,1,2,1],[2,2,1,0],[0,2,2,0],[1,1,1,1],[0,2,0,0],[2,2,0,1]]},"ryEsbb8tW":{"remainingCards":[[2,2,2,1],[0,0,2,1],[0,1,1,1],[0,2,2,1],[0,2,1,1],[1,1,2,0],[0,1,2,1],[2,2,1,2],[2,1,0,0],[1,1,1,1],[2,2,0,0],[1,2,0,0],[0,2,0,0],[0,0,0,1],[0,1,2,2],[1,0,0,2],[1,0,0,0],[2,2,1,1],[2,0,0,0],[2,0,2,1],[1,2,2,2],[0,2,0,2],[1,2,1,2],[1,0,2,1],[2,0,2,2],[2,1,0,2],[0,2,1,2],[2,0,2,0],[2,0,1,1],[1,1,1,2],[0,1,1,2],[1,0,2,0],[0,2,1,0],[1,2,1,0],[0,2,2,0],[1,0,1,1],[1,0,1,2],[1,1,0,0],[1,0,1,0],[2,1,1,1],[2,1,2,1],[1,1,2,1],[0,0,1,2],[2,0,0,2],[1,1,0,1],[0,2,2,2],[1,2,0,1],[1,2,0,2]],"started":true,"roomName":"dupa chuj","mode":"std","cardTimeout":0,"hash":"ryEsbb8tW","crossed":[],"players":{"b6Wf864l5oRQ444DV758kMvxYakvkd16":{"name":"dupa","io":[]}},"scoreboard":{"b6Wf864l5oRQ444DV758kMvxYakvkd16":{"score":7,"name":"dupa"}},"onBoard":[[2,1,2,2],[0,1,2,0],[0,2,0,1],[0,0,2,2],[2,2,0,1],[1,1,2,2],[2,0,1,0],[0,0,1,1],[1,0,2,2],[1,0,0,1],[2,2,2,0],[2,1,0,1]]},"rk8jWW8FW":{"remainingCards":[[2,0,2,2],[1,0,2,2],[0,0,2,1],[1,2,2,0],[1,0,0,1],[2,1,0,1],[2,1,0,2],[0,2,2,1],[2,2,1,2],[2,1,1,1],[0,2,1,1],[0,1,2,2],[1,1,1,0],[1,1,2,2],[0,2,0,1],[2,2,1,0],[2,0,1,2],[0,0,0,0],[2,0,2,0],[0,1,2,0],[1,0,0,0],[0,2,2,2],[0,0,1,1],[1,0,2,1],[0,1,2,1],[1,1,0,2],[0,0,2,2],[1,2,0,0],[0,0,0,1],[2,1,0,0],[0,1,0,1],[2,0,1,1],[2,2,0,0],[1,2,2,1],[1,1,1,2],[2,1,2,2],[1,2,1,2],[0,0,0,2],[0,2,1,2],[2,2,2,1],[1,0,1,1],[2,2,2,2],[2,0,0,1],[2,1,1,2],[0,1,1,0],[1,1,2,1],[0,0,1,0],[0,2,1,0],[2,1,2,0],[2,2,0,2],[2,2,0,1],[0,1,1,2],[1,2,1,1],[0,1,0,2],[1,1,1,1],[2,0,2,1],[1,0,1,2],[2,2,1,1],[0,2,0,0],[0,2,0,2],[2,0,0,2],[2,2,2,0],[0,2,2,0]],"started":true,"roomName":"dupa chuj","mode":"std","cardTimeout":0,"hash":"rk8jWW8FW","crossed":[],"players":{"NfIYGMqZ6u2t4ymuYB6vADJDVMkIfOJm":{"name":"dupa","io":["49koZ3lpX5OzT3L-AAAC"]}},"scoreboard":{"NfIYGMqZ6u2t4ymuYB6vADJDVMkIfOJm":{"score":2,"name":"dupa"}},"onBoard":[[0,0,1,2],[2,1,1,0],[1,0,0,2],[0,1,1,1],[1,2,2,2],[1,1,2,0],[1,2,0,2],[1,1,0,1],[2,1,2,1],[2,0,1,0],[1,2,0,1],[0,1,0,0]]},"BJkdtWLF-":{"remainingCards":[[1,1,2,1],[1,2,2,1],[0,2,0,0],[2,0,1,1],[0,0,2,2],[0,1,0,1],[0,0,0,1],[2,1,2,1],[2,0,2,2],[0,2,0,2],[2,0,0,0],[0,0,0,0],[1,0,2,0],[0,1,2,0],[0,1,0,0],[1,0,1,1],[0,1,1,1],[1,1,0,2],[1,2,0,2],[0,0,1,1],[2,2,1,0],[2,1,1,2],[2,0,2,1],[2,2,2,0],[2,1,1,0],[2,2,2,2],[1,2,2,0],[0,1,2,2],[2,0,1,0],[1,2,2,2],[1,1,0,1],[1,1,0,0],[2,2,1,1],[0,2,2,1],[1,1,2,2],[2,0,2,0],[1,0,1,2],[2,0,0,1],[0,0,2,1],[1,0,0,0],[0,0,1,0],[2,1,1,1],[2,2,0,2],[0,2,1,0],[1,2,0,0],[1,1,1,0],[2,2,1,2],[2,2,0,1],[2,1,2,2],[1,0,2,1],[0,0,2,0],[1,2,1,1],[2,2,2,1],[0,0,1,2],[0,2,2,2],[1,0,1,0],[1,1,2,0]],"started":true,"roomName":"dupa chuj","mode":"sup","cardTimeout":0,"hash":"BJkdtWLF-","crossed":[],"players":{"b6Wf864l5oRQ444DV758kMvxYakvkd16":{"name":"dupa","io":["0Q276x7keeRoavYVAAAF"]}},"scoreboard":{"b6Wf864l5oRQ444DV758kMvxYakvkd16":{"score":3,"name":"dupa"}},"onBoard":[[1,1,1,1],[0,2,0,1],[1,0,0,2],[2,2,0,0],[1,1,1,2],[2,1,0,0],[2,0,1,2],[0,0,0,2],[1,2,1,0],[0,1,2,1],[2,1,0,1],[0,2,1,1]]},"SyDQ74wYb":{"remainingCards":[[2,1,1,2],[0,0,1,0],[2,2,0,1],[1,0,0,2],[0,0,2,1],[2,0,1,2],[0,1,2,0],[1,0,0,1],[1,0,1,2],[2,1,0,0],[0,1,0,1],[0,2,1,0],[2,1,1,1],[0,2,0,2],[1,2,1,1],[0,0,1,2],[2,1,1,0],[2,0,2,1],[2,2,1,2],[2,1,2,2],[1,2,1,2],[1,1,2,1],[2,2,1,1],[0,2,2,1],[0,2,1,2],[1,2,0,1],[1,1,0,2],[1,2,2,1],[2,2,0,2],[1,1,1,2],[2,0,2,0],[1,0,1,1],[2,0,1,0],[2,1,0,2],[2,0,1,1],[2,1,2,1],[0,2,2,0],[1,1,0,1],[0,1,1,1],[2,2,1,0],[2,0,0,2],[0,1,1,2],[0,0,1,1],[1,0,1,0],[2,1,0,1],[1,0,2,0],[2,0,2,2],[0,0,0,1],[1,2,0,2],[0,2,0,0],[0,2,0,1],[2,2,0,0],[0,1,0,2],[0,0,0,2],[2,1,2,0],[2,0,0,1],[0,0,2,2],[1,2,2,0],[0,1,1,0],[1,1,2,2],[0,1,2,1],[0,2,2,2],[0,2,1,1],[1,2,2,2],[1,1,0,0],[0,0,2,0]],"started":true,"roomName":"dupa chuj","mode":"std","cardTimeout":0,"hash":"SyDQ74wYb","crossed":[],"players":{"SiogKwOxSVnFtVLYFmrPiHJ6W2bYH27N":{"name":"dupa","io":["SP2LYsppFK5uQwXXAAAD","EvZTQU6mQLSTBKScAAAE"]}},"scoreboard":{"SiogKwOxSVnFtVLYFmrPiHJ6W2bYH27N":{"score":1,"name":"dupa"}},"onBoard":[[2,2,2,0],[1,1,1,1],[0,1,0,0],[2,2,2,1],[1,0,2,2],[2,0,0,0],[2,2,2,2],[0,0,0,0],[1,0,2,1],[1,2,0,0],[0,1,2,2],[1,1,1,0]]},"rJwgL4wF-":{"remainingCards":[],"started":true,"roomName":"dupa chuj","mode":"std","cardTimeout":0,"hash":"rJwgL4wF-","crossed":[],"players":{"SiogKwOxSVnFtVLYFmrPiHJ6W2bYH27N":{"name":"dupa","io":["B54Yk6n489gfrLy8AAAF","J2ozqaorHrBKX2foAAAI","liKeZ-h2JO9Ld0oRAAAA","2l2lQypAX2l4_CuEAAAD","l3UEIQJ0IqgSYpMMAAAD"]}},"scoreboard":{"SiogKwOxSVnFtVLYFmrPiHJ6W2bYH27N":{"score":23,"name":"dupa"}},"onBoard":[[1,1,2,0],[2,2,1,2],[0,0,1,0],[1,1,2,1],[0,2,1,2],[0,2,2,0],[1,1,1,2],[2,0,0,2],[0,2,2,1],[0,0,0,2],[2,2,0,1],[0,2,0,2]]},"BkK-LVPFb":{"remainingCards":[[1,2,1,0],[2,0,0,1],[1,1,2,1],[2,1,1,1],[1,0,0,1],[0,1,1,1],[1,1,0,1],[1,0,0,0],[0,2,0,2],[1,0,1,0],[2,2,0,0],[1,1,1,0],[2,1,0,2],[1,0,2,2],[2,0,1,1],[0,0,2,0],[2,1,1,2],[0,1,2,2],[1,2,1,1],[2,2,1,1],[1,0,1,1],[2,2,2,1],[2,2,2,0],[0,1,1,0],[1,1,0,2],[1,0,2,0],[0,0,0,1],[2,2,2,2],[0,0,2,2],[2,2,0,1],[2,0,2,0],[2,0,1,2],[2,0,2,2],[0,1,2,1],[0,0,2,1],[1,2,2,2],[0,1,0,0],[1,2,2,1],[2,1,2,1],[1,1,1,2],[0,2,1,2],[0,1,1,2],[1,0,2,1],[2,1,0,1],[0,0,0,0],[2,1,2,0],[1,2,1,2],[1,2,0,0],[1,1,1,1],[2,0,0,0],[1,2,0,2],[1,1,0,0],[0,2,2,0],[0,1,2,0],[0,2,0,0],[2,2,1,2],[2,2,1,0],[0,1,0,2],[0,2,2,2],[1,2,2,0],[2,0,1,0],[2,1,1,0],[0,0,0,2],[1,0,0,2],[2,0,0,2],[1,1,2,2],[2,1,0,0],[1,2,0,1],[0,1,0,1]],"started":true,"roomName":"dupa chuj","mode":"std","cardTimeout":0,"hash":"BkK-LVPFb","crossed":[],"players":{"SiogKwOxSVnFtVLYFmrPiHJ6W2bYH27N":{"name":"dupa","io":["6DNParMkeSJSU985AAAH"]}},"scoreboard":{"SiogKwOxSVnFtVLYFmrPiHJ6W2bYH27N":{"score":0,"name":"dupa"}},"onBoard":[[0,0,1,0],[1,1,2,0],[0,0,1,2],[0,2,1,1],[2,1,2,2],[0,2,0,1],[1,0,1,2],[2,0,2,1],[0,2,2,1],[2,2,0,2],[0,0,1,1],[0,2,1,0]]},"BJQmLEwFW":{"remainingCards":[[1,0,1,2],[2,1,2,0],[2,2,2,0],[2,2,0,0],[2,2,2,2],[1,2,2,2],[2,2,1,2],[1,1,1,0],[1,1,2,1],[0,0,2,2],[2,0,1,0],[1,0,0,2],[2,0,1,1],[1,0,0,1],[0,0,2,0],[0,0,1,2],[1,2,2,1],[1,1,0,0],[1,1,2,0],[1,1,0,1],[0,2,0,0],[0,1,1,2],[0,1,2,1],[2,2,0,1],[0,0,1,1],[0,2,1,1],[2,2,1,1],[1,0,1,1],[2,2,1,0],[1,2,0,2],[0,1,2,0],[2,2,2,1],[2,1,0,1],[0,0,2,1],[1,2,0,0],[1,0,1,0],[0,2,2,0],[0,0,0,0],[1,0,2,1],[1,0,2,2],[2,1,2,1],[0,1,0,1],[0,1,0,0],[1,2,0,1],[0,2,0,2],[2,1,1,0],[2,0,1,2],[1,0,2,0],[2,0,0,0],[2,0,2,1],[0,2,0,1],[2,1,0,2],[2,1,1,2],[1,0,0,0],[1,1,0,2],[0,0,0,1],[2,0,0,2],[2,0,2,0],[1,2,1,0],[0,0,1,0],[2,1,1,1],[0,2,2,2],[0,1,0,2],[1,1,1,1],[2,0,2,2],[2,0,0,1],[0,2,1,2],[1,2,1,2],[1,1,2,2]],"started":true,"roomName":"dupa chuj","mode":"std","cardTimeout":0,"hash":"BJQmLEwFW","crossed":[],"players":{"SiogKwOxSVnFtVLYFmrPiHJ6W2bYH27N":{"name":"dupa","io":["7L3FPm34_d7bqljDAAAC"]}},"scoreboard":{"SiogKwOxSVnFtVLYFmrPiHJ6W2bYH27N":{"score":0,"name":"dupa"}},"onBoard":[[2,2,0,2],[1,1,1,2],[1,2,2,0],[2,1,0,0],[0,1,1,1],[2,1,2,2],[1,2,1,1],[0,2,2,1],[0,1,2,2],[0,1,1,0],[0,0,0,2],[0,2,1,0]]},"SyErIVwK-":{"remainingCards":[[2,2,1,2],[0,0,0,0],[2,0,2,1],[0,0,1,1],[0,0,0,1],[2,1,0,0],[0,2,2,1],[1,2,1,2],[0,2,1,2],[2,2,2,1],[2,1,1,0],[0,1,2,1],[2,2,1,0],[1,0,1,1],[1,0,1,0],[1,0,0,2],[0,0,0,2],[1,1,2,2],[1,2,2,2],[0,1,0,2],[2,0,0,0],[2,1,0,2],[0,1,1,2],[1,2,0,1],[1,0,0,0],[1,2,1,1],[0,2,1,1],[1,2,1,0],[0,1,2,0],[1,0,2,2],[2,0,2,2],[2,2,0,0],[1,1,1,1],[0,2,2,0],[2,1,2,1],[0,0,1,2],[0,0,2,0],[2,0,1,1],[2,2,0,2],[2,1,1,2],[0,0,1,0],[2,1,2,2],[1,0,2,1],[2,0,2,0],[1,1,0,1],[0,1,0,0],[2,0,0,2],[1,1,2,0],[2,1,0,1],[0,0,2,2],[2,0,1,2],[1,0,0,1],[0,0,2,1],[0,2,0,1],[0,1,0,1],[2,1,2,0],[2,1,1,1],[0,2,0,0],[0,2,2,2],[2,0,1,0],[1,2,2,1],[1,0,1,2],[0,1,2,2],[1,1,0,2],[1,1,0,0],[1,1,1,2],[1,1,1,0],[1,1,2,1],[0,1,1,0]],"started":true,"roomName":"dupa chuj","mode":"sup","cardTimeout":0,"hash":"SyErIVwK-","crossed":[],"players":{"SiogKwOxSVnFtVLYFmrPiHJ6W2bYH27N":{"name":"dupa","io":["ZcYm0Mrde0wpLNJoAAAC"]}},"scoreboard":{"SiogKwOxSVnFtVLYFmrPiHJ6W2bYH27N":{"score":0,"name":"dupa"}},"onBoard":[[2,2,2,0],[1,2,0,2],[1,0,2,0],[2,2,0,1],[0,1,1,1],[0,2,0,2],[2,2,2,2],[1,2,2,0],[1,2,0,0],[0,2,1,0],[2,0,0,1],[2,2,1,1]]},"rkkU84vt-":{"remainingCards":[[0,1,0,2],[2,1,1,2],[1,0,0,1],[0,0,0,2],[1,0,2,2],[0,2,0,0],[1,0,2,0],[2,0,2,2],[2,0,2,0],[2,2,1,2],[2,2,1,0],[2,2,2,1],[0,0,0,0],[1,1,0,0],[0,1,1,0],[2,2,0,1],[2,1,1,0],[1,0,1,1],[0,1,0,1],[2,1,2,2],[1,1,2,2],[1,2,1,2],[2,2,0,2],[2,0,1,1],[2,0,2,1],[0,0,1,0],[1,2,0,0],[2,2,1,1],[0,1,1,2],[1,0,1,2],[0,1,0,0],[0,0,1,2],[0,0,0,1],[0,2,0,2],[0,2,1,1],[2,0,1,0],[1,2,2,2],[0,0,1,1],[0,0,2,0],[1,2,0,1],[1,1,1,2],[1,0,2,1],[1,1,1,0],[2,2,0,0],[1,1,0,2],[0,1,1,1],[0,2,2,0],[1,1,1,1],[0,1,2,1],[0,2,1,2],[0,0,2,2],[2,0,0,2],[0,0,2,1],[2,2,2,2],[2,0,0,0],[0,1,2,0],[2,1,2,0],[1,1,0,1],[0,2,0,1],[1,2,1,0],[0,2,2,1],[1,1,2,0],[0,2,1,0],[2,1,0,2],[1,2,1,1],[1,0,0,2],[2,2,2,0],[1,2,2,1],[2,1,1,1]],"started":true,"roomName":"dupa chuj","mode":"sup","cardTimeout":0,"hash":"rkkU84vt-","crossed":[],"players":{"SiogKwOxSVnFtVLYFmrPiHJ6W2bYH27N":{"name":"dupa","io":["KQ7nNqkIS78QpJrbAAAC"]}},"scoreboard":{"SiogKwOxSVnFtVLYFmrPiHJ6W2bYH27N":{"score":0,"name":"dupa"}},"onBoard":[[2,0,1,2],[2,1,2,1],[0,1,2,2],[2,1,0,1],[2,1,0,0],[0,2,2,2],[1,0,0,0],[1,1,2,1],[2,0,0,1],[1,2,0,2],[1,2,2,0],[1,0,1,0]]},"SJ-68VwKb":{"remainingCards":[[0,2,1,0],[2,1,1,1],[2,0,2,2],[2,0,1,1],[0,1,2,1],[0,0,0,2],[1,1,0,1],[2,2,1,2],[2,1,2,0],[1,2,2,1],[0,0,1,1],[2,0,0,1],[1,2,1,2],[2,1,0,2],[1,0,2,0],[1,2,1,1],[2,1,0,0],[2,1,1,0],[1,1,0,2],[0,0,1,0],[2,0,0,0],[0,1,0,1],[0,2,2,1],[2,2,2,1],[0,2,1,1],[2,2,2,2],[2,0,2,0],[1,2,0,1],[0,2,1,2],[0,2,2,2],[2,0,0,2],[1,2,1,0],[0,1,1,0],[1,1,1,1],[1,2,2,2],[2,1,2,1],[2,0,2,1],[2,1,2,2],[1,1,0,0],[2,2,1,0],[1,0,0,2],[0,2,0,0],[0,2,2,0],[1,2,2,0],[0,0,2,2],[0,2,0,1],[1,0,1,1],[0,1,2,2],[0,1,1,1],[0,0,1,2],[2,2,1,1],[1,1,1,2],[1,0,0,0],[0,1,0,0],[0,0,2,0],[0,0,0,1],[1,1,2,0],[1,0,2,1],[2,0,1,2],[0,0,2,1],[1,1,1,0],[2,2,0,0],[2,1,1,2]],"started":true,"roomName":"dupa chuj","mode":"std","cardTimeout":"0","hash":"SJ-68VwKb","crossed":[],"players":{"SiogKwOxSVnFtVLYFmrPiHJ6W2bYH27N":{"name":"dupa","io":["56Q0adOZtQY5urhMAAAC"]}},"scoreboard":{"SiogKwOxSVnFtVLYFmrPiHJ6W2bYH27N":{"score":2,"name":"dupa"}},"onBoard":[[2,2,2,0],[1,0,0,1],[0,1,1,2],[2,1,0,1],[1,0,2,2],[2,0,1,0],[0,1,0,2],[1,0,1,0],[0,0,0,0],[1,1,2,1],[1,1,2,2],[1,2,0,0]]},"rk-GlIPKZ":{"remainingCards":[],"started":true,"roomName":"dupa chuj","mode":"sup","cardTimeout":0,"hash":"rk-GlIPKZ","crossed":[],"players":{"SiogKwOxSVnFtVLYFmrPiHJ6W2bYH27N":{"name":"dupa","io":["rEkKJwIJLJ3tfmtvAAAD"]}},"scoreboard":{"SiogKwOxSVnFtVLYFmrPiHJ6W2bYH27N":{"score":19,"name":"dupa"}},"onBoard":[[0,1,0,2],[2,2,2,1],[1,0,2,0],[0,0,1,0],[2,2,1,2]]},"BJsIRcFK-":{"remainingCards":[[1,0,0,0],[2,1,1,1],[2,1,1,0],[0,2,0,1],[1,1,1,2],[0,1,0,1],[2,0,2,0],[1,0,1,0],[2,1,0,2],[0,0,2,1],[2,2,1,0],[2,1,2,0],[1,0,2,0],[2,1,2,2],[2,1,0,0],[2,2,2,2],[0,1,1,0],[2,1,0,1],[0,2,1,0],[1,2,0,0],[1,1,1,0],[1,1,1,1],[0,1,0,2],[2,2,1,2],[0,1,1,2],[0,1,2,2],[1,0,1,1],[2,2,0,1],[1,1,0,1],[2,0,0,1],[0,0,0,2],[2,2,1,1],[2,2,2,0],[1,2,0,2],[1,1,2,0],[2,2,0,0],[2,2,0,2],[0,2,2,0],[0,2,0,0],[0,2,2,2],[2,2,2,1],[0,0,2,2],[1,1,0,0],[2,0,1,1],[0,0,0,1],[1,0,2,1],[1,2,2,2],[0,2,0,2],[0,0,1,1],[1,0,2,2],[0,1,0,0],[1,0,0,2],[0,2,1,2],[1,1,0,2],[2,1,1,2],[1,2,2,1],[0,0,2,0],[2,0,0,0],[1,2,1,0],[0,0,1,2],[0,0,0,0],[2,0,2,1],[1,2,1,2],[1,0,0,1],[1,2,2,0],[2,1,2,1],[0,0,1,0],[2,0,0,2],[1,1,2,1]],"started":true,"roomName":"dupa chuj","mode":"sup","cardTimeout":0,"hash":"BJsIRcFK-","crossed":[],"players":{"OHm5V2Qz7ZEtktlpisEGQ59xnoOQrzvt":{"name":"dupa","io":["Crum7WK0RsfJSWPXAAAA"]}},"scoreboard":{"OHm5V2Qz7ZEtktlpisEGQ59xnoOQrzvt":{"score":0,"name":"dupa"}},"onBoard":[[0,1,2,0],[0,2,1,1],[1,2,1,1],[0,1,2,1],[2,0,1,2],[2,0,1,0],[1,1,2,2],[0,2,2,1],[0,1,1,1],[1,0,1,2],[1,2,0,1],[2,0,2,2]]},"SJ1vXLB9W":{"remainingCards":[[0,2,0,2],[1,0,1,1],[1,2,0,0],[1,1,1,1],[0,0,0,2],[1,2,1,1],[0,1,2,0],[1,1,0,2],[1,0,2,2],[1,2,2,0],[2,2,2,2],[1,1,1,2],[1,2,0,1],[0,1,1,0],[1,1,2,1],[2,2,0,2],[2,0,1,0],[2,0,2,1],[1,0,1,0],[0,1,0,2],[1,1,1,0],[0,1,0,1],[2,1,1,2],[1,1,2,2],[1,2,1,2],[1,0,2,1],[2,0,0,2],[0,2,2,1],[0,0,2,2],[1,0,1,2],[0,2,1,0],[1,0,0,2],[0,2,0,0],[0,0,0,0],[2,1,2,1],[2,0,1,1],[2,2,1,2],[0,0,2,1],[2,0,0,0],[0,2,1,1],[0,2,2,2],[1,2,0,2],[2,2,0,0],[1,0,0,1],[2,0,2,0],[2,2,2,1],[0,2,1,2],[2,0,0,1],[2,1,0,0],[0,1,2,2],[0,1,1,2],[2,1,1,0],[1,0,0,0],[2,1,0,1],[1,2,1,0],[0,0,1,1],[1,2,2,1],[0,0,0,1],[2,1,2,2],[2,0,1,2],[1,1,0,0],[0,1,2,1],[0,1,0,0],[1,1,0,1],[0,2,2,0],[0,0,1,0]],"started":true,"roomName":"dupa chuj","mode":"std","cardTimeout":0,"hash":"SJ1vXLB9W","crossed":[],"players":{"YNMn1O1OhVJm9Ke81ZbYXx8YqcCeD9C7":{"name":"dupa","io":["IO7EEeyxSxy7DYBLAAAA"]}},"scoreboard":{"YNMn1O1OhVJm9Ke81ZbYXx8YqcCeD9C7":{"score":1,"name":"dupa"}},"onBoard":[[0,2,0,1],[0,0,1,2],[2,2,1,0],[1,2,2,2],[2,2,1,1],[0,1,1,1],[2,0,2,2],[2,1,2,0],[2,1,0,2],[2,1,1,1],[1,0,2,0],[2,2,0,1]]}},"accounts":{},"sessions":{"NfIYGMqZ6u2t4ymuYB6vADJDVMkIfOJm":{},"b6Wf864l5oRQ444DV758kMvxYakvkd16":{},"4TjyBqtg5zCgu07RVgdSY2FTk8jm5Lrl":{},"4hvpcCQyujXAxoLDmZ9rRxNY0CSiGkqA":{},"LH07KkkTro5EXDK94IPJm2V22lHewAUv":{},"nRpHsa84u7EWAesp9TXhR8aHkyyUS3nC":{},"dsCE6VmWVSjQ7d9DVCcPXPPHOSwPRuHV":{},"WyGTY2JHBtI3yzFjTnFi96AAIfDbP5Bk":{},"rp0Rrq9knr7XDyVnUs2td4lbN28mwxfH":{},"fBONS2mJep2bVBhYoYIoVDhksG84WXI5":{},"O0EaSAOmFCGHoByMyUWpxO7RPPLMl5PK":{},"Ie6lVyrlL7nUngv3Q9d0zABI3srhnHbk":{},"CwJDNyYE2pStXlHoWNzWKUgPFDoSbtPd":{},"0oRfEnGT6opTHPqQ3DodicXFwjjBsFr4":{},"nDGHae7hMwZ3qtGAanMKrT6zUkzu0QR2":{},"bhIaQfMKVjhU05YWEfkP1cPaU7QwHaJf":{},"DF3QxG9ZxwitzRJuN2CGffXqhUhcOniw":{},"GLAgzq7wBzZzmFUtyK0rtz07qIwxe5FS":{},"fylgtRE9iGPEvHx2axcv1xSqTq1xsDJI":{},"SiogKwOxSVnFtVLYFmrPiHJ6W2bYH27N":{},"zPQ6qLs2cbus6c5ueqQjmPMI7txzqONY":{},"OHm5V2Qz7ZEtktlpisEGQ59xnoOQrzvt":{},"YNMn1O1OhVJm9Ke81ZbYXx8YqcCeD9C7":{}}}